torchwebio/__init__.py
torchwebio/exceptions.py
torchwebio/webalyzer.py
torchwebio/models/__init__.py
torchwebio/models/image/__init__.py
torchwebio/models/image/imageclassificationmodel.py
torchwebio-0.0.2.dist-info/LICENSE.txt
torchwebio-0.0.2.dist-info/METADATA
torchwebio-0.0.2.dist-info/WHEEL
torchwebio-0.0.2.dist-info/top_level.txt
torchwebio-0.0.2.dist-info/RECORD
