Metadata-Version: 2.1
Name: torchwebio
Version: 0.0.2
Summary: Turn your pyTorch model into a web app
Home-page: https://github.com/pyscaffold/pyscaffold/
Author: Prass, The Nomadic Coder
Author-email: me@prassanna.io
License: MIT
Project-URL: Documentation, https://pyscaffold.org/
Platform: any
Classifier: Development Status :: 4 - Beta
Classifier: Programming Language :: Python
License-File: LICENSE.txt
Requires-Dist: timm (==0.6.7)
Requires-Dist: pywebio (==1.6.2)
Requires-Dist: importlib-metadata ; python_version < "3.8"
Provides-Extra: dev
Requires-Dist: setuptools ; extra == 'dev'
Requires-Dist: pytest ; extra == 'dev'
Requires-Dist: pytest-cov ; extra == 'dev'
Requires-Dist: pre-commit ; extra == 'dev'
Requires-Dist: pytest-subtests ; extra == 'dev'
Requires-Dist: tox ; extra == 'dev'
